tracecolor/__init__.py
tracecolor/monitor.py
tracecolor/run_monitor.py
tracecolor/test_udp.py
tracecolor/tracecolor.py
tracecolor-0.7.16.dist-info/licenses/LICENSE
tracecolor-0.7.16.dist-info/METADATA
tracecolor-0.7.16.dist-info/WHEEL
tracecolor-0.7.16.dist-info/entry_points.txt
tracecolor-0.7.16.dist-info/top_level.txt
tracecolor-0.7.16.dist-info/RECORD
