Metadata-Version: 2.4
Name: tracecolor
Version: 0.7.16
Summary: Enhanced Python logger with colorized output, TRACE/PROGRESS levels, UDP monitoring, file logging, and external config support via Loguru backend.
Home-page: https://github.com/marcodelpin/tracecolor
Author: Marco Del Pin
Author-email: Marco Del Pin <marco.delpin@gmail.com>
License: MIT License
Project-URL: Homepage, https://github.com/marcodelpin/tracecolor
Project-URL: Issues, https://github.com/marcodelpin/tracecolor/issues
Classifier: Programming Language :: Python :: 3
Classifier: Operating System :: OS Independent
Requires-Python: >=3.8
License-File: LICENSE
Requires-Dist: loguru>=0.7.2
Requires-Dist: colorlog>=6.0.0
Provides-Extra: yaml
Requires-Dist: pyyaml>=6.0; extra == "yaml"
Provides-Extra: dev
Requires-Dist: pytest>=7.0; extra == "dev"
Requires-Dist: pytest-cov>=4.0; extra == "dev"
Requires-Dist: black>=22.0; extra == "dev"
Requires-Dist: flake8>=5.0; extra == "dev"
Requires-Dist: mypy>=0.990; extra == "dev"
Dynamic: author
Dynamic: home-page
Dynamic: license-file
Dynamic: requires-python
